sphinxnotes_peopledomain-0.2-py3.8-nspkg.pth
sphinxnotes/peopledomain.py
sphinxnotes_peopledomain-0.2.dist-info/LICENSE
sphinxnotes_peopledomain-0.2.dist-info/METADATA
sphinxnotes_peopledomain-0.2.dist-info/WHEEL
sphinxnotes_peopledomain-0.2.dist-info/namespace_packages.txt
sphinxnotes_peopledomain-0.2.dist-info/top_level.txt
sphinxnotes_peopledomain-0.2.dist-info/RECORD
