Metadata-Version: 2.1
Name: sphinxnotes-peopledomain
Version: 0.2
Summary: Sphinx domain for describing people
Home-page: https://github.com/sphinx-notes/peopledomain
Author: Shengyu Zhang
Author-email: UNKNOWN
License: BSD
Download-URL: https://pypi.org/project/sphinxnotes-peopledomain/
Platform: any
Classifier: Development Status :: 3 - Alpha
Classifier: Environment :: Console
Classifier: Environment :: Web Environment
Classifier: Intended Audience :: Developers
Classifier: License :: OSI Approved :: BSD License
Classifier: Operating System :: OS Independent
Classifier: Programming Language :: Python
Classifier: Programming Language :: Python :: 3.5
Classifier: Programming Language :: Python :: 3.6
Classifier: Topic :: Documentation
Classifier: Topic :: Utilities
Requires-Dist: Sphinx (>=1.5)
